tests/__init__.py
tests/test_bot.py
tests/test_objects.py
ttbotapi/__init__.py
ttbotapi/bot.py
ttbotapi/methods.py
ttbotapi/objects.py
ttbotapi/utils/__init__.py
ttbotapi/utils/api_exceptions.py
ttbotapi/utils/api_functions.py
ttbotapi/utils/api_handler.py
ttbotapi/utils/json_helper.py
ttbotapi/utils/logger.py
ttbotapi-0.3.0.dist-info/LICENSE
ttbotapi-0.3.0.dist-info/METADATA
ttbotapi-0.3.0.dist-info/WHEEL
ttbotapi-0.3.0.dist-info/top_level.txt
ttbotapi-0.3.0.dist-info/RECORD
