Metadata-Version: 2.1
Name: ttbotapi
Version: 0.3.0
Summary: TamTam Bot API library
Home-page: https://github.com/MA24th/tgbotapi
Author: Mustafa Asaad
Author-email: ma24th@yahoo.com
License: GNU GPLv2
Platform: UNKNOWN
Classifier: Development Status :: 5 - Production/Stable
Classifier: Programming Language :: Python :: 3.6
Classifier: Programming Language :: Python :: 3.7
Classifier: Programming Language :: Python :: 3.8
Classifier: Programming Language :: Python :: 3.9
Classifier: License :: OSI Approved :: GNU General Public License v2 (GPLv2)
License-File: LICENSE
Requires-Dist: requests
